LICENSE
MANIFEST.in
README.md
requirements.txt
setup.cfg
setup.py
versioneer.py
occa/__init__.py
occa/_version.py
occa/base.py
occa/device.py
occa/dtype.py
occa/exceptions.py
occa/kernel.py
occa/memory.py
occa/stream.py
occa/streamtag.py
occa/utils.py
occa.egg-info/PKG-INFO
occa.egg-info/SOURCES.txt
occa.egg-info/dependency_links.txt
occa.egg-info/not-zip-safe
occa.egg-info/requires.txt
occa.egg-info/top_level.txt
occa/c/__init__.py
occa/c/base.cpp
occa/c/defines.hpp
occa/c/device.cpp
occa/c/dtype.cpp
occa/c/errors.hpp
occa/c/header.hpp
occa/c/kernel.cpp
occa/c/kwargparser.hpp
occa/c/memory.cpp
occa/c/stream.cpp
occa/c/streamtag.cpp
occa/c/toPy.hpp
occa/c/types.hpp
occa/c/occa.git/LICENSE
occa/c/occa.git/Makefile
occa/c/occa.git/bin/occa
occa/c/occa.git/bin/occa.cpp
occa/c/occa.git/examples/cpp/1_add_vectors/main.cpp
occa/c/occa.git/examples/cpp/2_background_device/main.cpp
occa/c/occa.git/examples/cpp/3_reduction/main.cpp
occa/c/occa.git/examples/cpp/4_building_kernels/main.cpp
occa/c/occa.git/examples/cpp/5_unified_memory/main.cpp
occa/c/occa.git/examples/cpp/6_dtypes/main.cpp
occa/c/occa.git/examples/cpp/7_arrays/main.cpp
occa/c/occa.git/examples/cpp/8_streams/main.cpp
occa/c/occa.git/examples/cpp/9_mpi/main.cpp
occa/c/occa.git/examples/cpp/interop_examples/cuda/main.cpp
occa/c/occa.git/examples/cpp/interop_examples/native/addVectors/addVectors.cpp
occa/c/occa.git/examples/cpp/interop_examples/native/addVectors/main.cpp
occa/c/occa.git/examples/cpp/interop_examples/native/reduction/main.cpp
occa/c/occa.git/examples/cpp/interop_examples/opencl/main.cpp
occa/c/occa.git/examples/cpp/interop_examples/openmp/main.cpp
occa/c/occa.git/examples/cpp/opengl_examples/fd2d/main.cpp
occa/c/occa.git/examples/cpp/opengl_examples/fd2d/include/visualizer.hpp
occa/c/occa.git/examples/cpp/opengl_examples/fd2d/src/visualizer.cpp
occa/c/occa.git/examples/cpp/opengl_examples/mandelbulb/main.cpp
occa/c/occa.git/examples/cpp/opengl_examples/mandelbulb/include/visualizer.hpp
occa/c/occa.git/examples/cpp/opengl_examples/mandelbulb/src/visualizer.cpp
occa/c/occa.git/include/occa.h
occa/c/occa.git/include/occa.hpp
occa/c/occa.git/include/occa/array.hpp
