Metadata-Version: 1.1
Name: occa
Version: 0.4.1
Summary: Portable Approach for Parallel Architectures
Home-page: https://libocca.org
Author: David Medina
Author-email: UNKNOWN
License: MIT
Keywords: occa,hpc,gpu,jit,openmp,opencl,cuda
Platform: UNKNOWN
Classifier: Development Status :: 3 - Alpha
Classifier: Intended Audience :: Developers
Classifier: Intended Audience :: Science/Research
Classifier: License :: OSI Approved :: MIT License
Classifier: Operating System :: MacOS
Classifier: Operating System :: POSIX
Classifier: Operating System :: Unix
Classifier: Programming Language :: Python :: 3
Classifier: Programming Language :: Python :: 3.6
Classifier: Programming Language :: Python :: 3.7
Classifier: Programming Language :: Python :: Implementation :: CPython
Classifier: Topic :: Scientific/Engineering
Classifier: Topic :: Software Development
